xweb.py
xweb-3.0.1.dist-info/LICENSE.md
xweb-3.0.1.dist-info/METADATA
xweb-3.0.1.dist-info/WHEEL
xweb-3.0.1.dist-info/top_level.txt
xweb-3.0.1.dist-info/RECORD
