Metadata-Version: 2.1
Name: xweb
Version: 3.0.1
Summary: High performance web framework built with uvloop and httptools.
Home-page: https://github.com/gaojiuli/xweb
Author: gaojiuli
Author-email: gaojiuli@gmail.com
License: MIT
Platform: any
Classifier: Development Status :: 3 - Alpha
Classifier: Intended Audience :: Developers
Classifier: License :: OSI Approved :: MIT License
Classifier: Topic :: Internet :: WWW/HTTP :: Dynamic Content :: CGI Tools/Libraries
Classifier: Topic :: Internet :: WWW/HTTP :: HTTP Servers
Classifier: Topic :: Software Development :: Libraries :: Application Frameworks
Classifier: Programming Language :: Python :: 3.6
Classifier: Programming Language :: Python :: 3.7
Requires-Dist: asyncio
Requires-Dist: ujson
Requires-Dist: uvloop
Requires-Dist: httptools
Requires-Dist: gunicorn
Requires-Dist: jsonschema
